simplesoapy
