Metadata-Version: 1.1
Name: SimpleSoapy
Version: 1.5.1
Summary: Simple pythonic wrapper for SoapySDR library
Home-page: https://github.com/xmikos/simplesoapy
Author: Michal Krenek (Mikos)
Author-email: m.krenek@gmail.com
License: MIT
Platform: UNKNOWN
Classifier: Development Status :: 4 - Beta
Classifier: Intended Audience :: Developers
Classifier: Intended Audience :: Science/Research
Classifier: Intended Audience :: Telecommunications Industry
Classifier: License :: OSI Approved :: MIT License
Classifier: Natural Language :: English
Classifier: Operating System :: OS Independent
Classifier: Programming Language :: Python :: 3
Classifier: Topic :: Software Development :: Libraries :: Python Modules
Classifier: Topic :: Scientific/Engineering
Classifier: Topic :: Communications :: Ham Radio
